spasco/__init__.py
spasco/main.py
spasco/term_color.py
tests/__init__.py
tests/check_names.py
tests/main_test.py
spasco-1.0.1.dist-info/LICENSE
spasco-1.0.1.dist-info/METADATA
spasco-1.0.1.dist-info/WHEEL
spasco-1.0.1.dist-info/entry_points.txt
spasco-1.0.1.dist-info/top_level.txt
spasco-1.0.1.dist-info/RECORD
